sample/__init__.py
sample/package_data.dat
sample/simple.py
BrewPi_Remix-0.0.0.1.dist-info/LICENSE
BrewPi_Remix-0.0.0.1.dist-info/METADATA
BrewPi_Remix-0.0.0.1.dist-info/WHEEL
BrewPi_Remix-0.0.0.1.dist-info/dependency_links.txt
BrewPi_Remix-0.0.0.1.dist-info/top_level.txt
BrewPi_Remix-0.0.0.1.dist-info/RECORD
